odoo/addons/users_ldap_mail/README.rst
odoo/addons/users_ldap_mail/__init__.py
odoo/addons/users_ldap_mail/__manifest__.py
odoo/addons/users_ldap_mail/i18n/de.po
odoo/addons/users_ldap_mail/i18n/es.po
odoo/addons/users_ldap_mail/i18n/fr.po
odoo/addons/users_ldap_mail/i18n/hr.po
odoo/addons/users_ldap_mail/i18n/hr_HR.po
odoo/addons/users_ldap_mail/i18n/it.po
odoo/addons/users_ldap_mail/i18n/pt_BR.po
odoo/addons/users_ldap_mail/i18n/sl.po
odoo/addons/users_ldap_mail/i18n/users_ldap_mail.pot
odoo/addons/users_ldap_mail/i18n/zh_CN.po
odoo/addons/users_ldap_mail/models/__init__.py
odoo/addons/users_ldap_mail/models/users_ldap_model.py
odoo/addons/users_ldap_mail/readme/CONTRIBUTORS.md
odoo/addons/users_ldap_mail/readme/DESCRIPTION.md
odoo/addons/users_ldap_mail/readme/ROADMAP.md
odoo/addons/users_ldap_mail/readme/USAGE.md
odoo/addons/users_ldap_mail/static/description/icon.png
odoo/addons/users_ldap_mail/static/description/index.html
odoo/addons/users_ldap_mail/views/res_company_ldap.xml
odoo_addon_users_ldap_mail-18.0.1.0.0.2.dist-info/METADATA
odoo_addon_users_ldap_mail-18.0.1.0.0.2.dist-info/WHEEL
odoo_addon_users_ldap_mail-18.0.1.0.0.2.dist-info/top_level.txt
odoo_addon_users_ldap_mail-18.0.1.0.0.2.dist-info/RECORD
