Metadata-Version: 2.1
Name: odoo-addon-users_ldap_mail
Version: 18.0.1.0.0.2
Requires-Python: >=3.10
Requires-Dist: odoo==18.0.*
Summary: LDAP mapping for user name and e-mail
Home-page: https://github.com/OCA/server-auth
License: AGPL-3
Author: Daniel Reis,Odoo Community Association (OCA)
Author-email: support@odoo-community.org
Classifier: Programming Language :: Python
Classifier: Framework :: Odoo
Classifier: Framework :: Odoo :: 18.0
Classifier: License :: OSI Approved :: GNU Affero General Public License v3
